{
    "1722166883305025617": {
        "author_id": "29191062",
        "created_at": "2023-11-08T08:19:15.000Z",
        "edit_history_tweet_ids": [
            "1722166883305025617"
        ],
        "entities": {
            "mentions": [
                {
                    "end": 16,
                    "id": "627673190",
                    "start": 0,
                    "username": "ChampionsLeague"
                },
                {
                    "end": 25,
                    "id": "21390674",
                    "start": 17,
                    "username": "FCPorto"
                },
                {
                    "end": 39,
                    "id": "333534411",
                    "start": 26,
                    "username": "officialpepe"
                }
            ]
        },
        "id": "1722166883305025617",
        "lang": "en",
        "public_metrics": {
            "bookmark_count": 0,
            "impression_count": 1084,
            "like_count": 20,
            "quote_count": 0,
            "reply_count": 0,
            "retweet_count": 1
        },
        "text": "@ChampionsLeague @FCPorto @officialpepe Aging like fine beer!"
    }
}