{
    "1616040488489951234": {
        "attachments": {
            "media_keys": [
                "7_1616040307254038530"
            ]
        },
        "author_id": "380801406",
        "created_at": "2023-01-19T11:50:51.000Z",
        "edit_history_tweet_ids": [
            "1616040488489951234"
        ],
        "entities": {
            "annotations": [
                {
                    "end": 56,
                    "normalized_text": "Chile",
                    "probability": 0.9448,
                    "start": 52,
                    "type": "Place"
                },
                {
                    "end": 66,
                    "normalized_text": "Alaska",
                    "probability": 0.9835,
                    "start": 61,
                    "type": "Place"
                },
                {
                    "end": 109,
                    "normalized_text": "Julian Pueschel",
                    "probability": 0.5675,
                    "start": 95,
                    "type": "Person"
                },
                {
                    "end": 163,
                    "normalized_text": "Pan-America",
                    "probability": 0.5281,
                    "start": 153,
                    "type": "Place"
                },
                {
                    "end": 172,
                    "normalized_text": "Maersk",
                    "probability": 0.5402,
                    "start": 167,
                    "type": "Place"
                }
            ],
            "hashtags": [
                {
                    "end": 173,
                    "start": 166,
                    "tag": "Maersk"
                },
                {
                    "end": 190,
                    "start": 174,
                    "tag": "purposeinaction"
                },
                {
                    "end": 203,
                    "start": 192,
                    "tag": "panamerica"
                }
            ],
            "urls": [
                {
                    "display_url": "bddy.me/3wcQGOG",
                    "end": 258,
                    "expanded_url": "https://bddy.me/3wcQGOG",
                    "start": 235,
                    "url": "https://t.co/hEK49CJ3j3"
                },
                {
                    "display_url": "pic.twitter.com/AsepKg8nYz",
                    "end": 282,
                    "expanded_url": "https://twitter.com/Maersk/status/1616040488489951234/video/1",
                    "media_key": "7_1616040307254038530",
                    "start": 259,
                    "url": "https://t.co/AsepKg8nYz"
                }
            ]
        },
        "id": "1616040488489951234",
        "lang": "en",
        "public_metrics": {
            "bookmark_count": 0,
            "impression_count": 3672,
            "like_count": 29,
            "quote_count": 0,
            "reply_count": 2,
            "retweet_count": 2
        },
        "text": "Vroom \ud83c\udfcd take the motorcycle ride of a lifetime from Chile to Alaska \ud83c\udf0e with our Product Manager Julian Pueschel, \ud83d\udcf1capturing the communities stories along Pan-America. #Maersk #purposeinaction  #panamerica. Watch the first episode here: https://t.co/hEK49CJ3j3 https://t.co/AsepKg8nYz"
    }
}