{
    "1686013881141870594": {
        "attachments": {
            "media_keys": [
                "3_1686013874384838657"
            ]
        },
        "author_id": "380801406",
        "created_at": "2023-07-31T14:00:08.000Z",
        "edit_history_tweet_ids": [
            "1686013881141870594"
        ],
        "entities": {
            "annotations": [
                {
                    "end": 44,
                    "normalized_text": "SupplyChainInnovation",
                    "probability": 0.538,
                    "start": 24,
                    "type": "Other"
                },
                {
                    "end": 54,
                    "normalized_text": "Maersk",
                    "probability": 0.4855,
                    "start": 49,
                    "type": "Other"
                },
                {
                    "end": 81,
                    "normalized_text": "Global Innovation Center",
                    "probability": 0.7649,
                    "start": 58,
                    "type": "Other"
                },
                {
                    "end": 270,
                    "normalized_text": "MaerskInnovationCenter",
                    "probability": 0.4256,
                    "start": 249,
                    "type": "Other"
                }
            ],
            "hashtags": [
                {
                    "end": 45,
                    "start": 23,
                    "tag": "SupplyChainInnovation"
                },
                {
                    "end": 247,
                    "start": 225,
                    "tag": "SupplyChainInnovation"
                },
                {
                    "end": 271,
                    "start": 248,
                    "tag": "MaerskInnovationCenter"
                }
            ],
            "urls": [
                {
                    "display_url": "bddy.me/3Oe5hSD",
                    "end": 223,
                    "expanded_url": "https://bddy.me/3Oe5hSD",
                    "start": 200,
                    "unwound_url": "https://www.maersk.com/news/articles/2023/07/21/north-america-market-update-july?utm_source=Twitter&utm_medium=organicpost&utm_campaign=M_5D28D5200753A_64B98195473E9&utm_term=VOCP&utm_content=NAM_3PL#topics-trends-insights",
                    "url": "https://t.co/hUr7d85Ho0"
                },
                {
                    "display_url": "pic.twitter.com/eXjZrVurQN",
                    "end": 295,
                    "expanded_url": "https://twitter.com/Maersk/status/1686013881141870594/photo/1",
                    "media_key": "3_1686013874384838657",
                    "start": 272,
                    "url": "https://t.co/eXjZrVurQN"
                }
            ]
        },
        "id": "1686013881141870594",
        "lang": "en",
        "public_metrics": {
            "bookmark_count": 0,
            "impression_count": 3358,
            "like_count": 29,
            "quote_count": 0,
            "reply_count": 0,
            "retweet_count": 5
        },
        "text": "Dive into the world of #SupplyChainInnovation at Maersk's Global Innovation Center. Exchange ideas, learn about state-of-the-art technologies and co-create solutions for your supply chain challenges.\nhttps://t.co/hUr7d85Ho0 \n#SupplyChainInnovation #MaerskInnovationCenter https://t.co/eXjZrVurQN"
    }
}