{
    "1642855758030155776": {
        "author_id": "92224801",
        "created_at": "2023-04-03T11:45:10.000Z",
        "edit_history_tweet_ids": [
            "1642855758030155776"
        ],
        "entities": {
            "mentions": [
                {
                    "end": 13,
                    "id": "1563172235329736704",
                    "start": 0,
                    "username": "Soulstorm002"
                }
            ]
        },
        "id": "1642855758030155776",
        "lang": "de",
        "public_metrics": {
            "bookmark_count": 0,
            "impression_count": 76,
            "like_count": 0,
            "quote_count": 0,
            "reply_count": 2,
            "retweet_count": 0
        },
        "text": "@Soulstorm002 Im Gegenteil. Es geht darum, zu zeigen, wie sehr Hetze, Beleidigungen und Beschimpfungen Menschen verletzen. Die Telekom will sensibilisieren, Opfern von Hass im Netz oder Cybermobbing den R\u00fccken st\u00e4rken und zu einem gemeinsamen Kampf gegen Hass im Netz aufrufen. ^anne"
    }
}