{
    "1712012861453533597": {
        "attachments": {
            "media_keys": [
                "3_1712012857196339200"
            ]
        },
        "author_id": "92224801",
        "created_at": "2023-10-11T07:50:48.000Z",
        "edit_history_tweet_ids": [
            "1712012861453533597"
        ],
        "entities": {
            "mentions": [
                {
                    "end": 8,
                    "id": "365687436",
                    "start": 0,
                    "username": "ulid000"
                },
                {
                    "end": 20,
                    "id": "892018950321688579",
                    "start": 9,
                    "username": "radkolumne"
                }
            ],
            "urls": [
                {
                    "display_url": "pic.twitter.com/KL9WnMzAra",
                    "end": 99,
                    "expanded_url": "https://twitter.com/deutschetelekom/status/1712012861453533597/photo/1",
                    "media_key": "3_1712012857196339200",
                    "start": 76,
                    "url": "https://t.co/KL9WnMzAra"
                }
            ]
        },
        "id": "1712012861453533597",
        "lang": "de",
        "public_metrics": {
            "bookmark_count": 0,
            "impression_count": 236,
            "like_count": 2,
            "quote_count": 0,
            "reply_count": 0,
            "retweet_count": 0
        },
        "text": "@ulid000 @radkolumne Danke f\u00fcr die Bilder. So sieht es 2023 aus. \ud83d\udeb2 ^karsten https://t.co/KL9WnMzAra"
    }
}