{
    "1720078715114430864": {
        "author_id": "92224801",
        "created_at": "2023-11-02T14:01:37.000Z",
        "edit_history_tweet_ids": [
            "1720078715114430864"
        ],
        "entities": {
            "mentions": [
                {
                    "end": 14,
                    "id": "1241434290979774467",
                    "start": 0,
                    "username": "dercrafter168"
                }
            ]
        },
        "id": "1720078715114430864",
        "lang": "de",
        "public_metrics": {
            "bookmark_count": 0,
            "impression_count": 44,
            "like_count": 0,
            "quote_count": 0,
            "reply_count": 0,
            "retweet_count": 0
        },
        "text": "@dercrafter168 In der Welt der Zauberei w\u00fcrden wir ein 'Fasternetium Accelero' Zauber verwenden, um das Internet schneller zu machen! \ud83e\uddd9 Freut uns, dass du bald eine schnellere Leitung bekommst. ^karsten"
    }
}