{
    "1721822323114758263": {
        "attachments": {
            "media_keys": [
                "3_1721822320774316032"
            ]
        },
        "author_id": "21746077",
        "created_at": "2023-11-07T09:30:06.000Z",
        "edit_history_tweet_ids": [
            "1721822323114758263"
        ],
        "entities": {
            "annotations": [
                {
                    "end": 39,
                    "normalized_text": "UK",
                    "probability": 0.9806,
                    "start": 38,
                    "type": "Place"
                },
                {
                    "end": 104,
                    "normalized_text": "Centrica Carers Network",
                    "probability": 0.7121,
                    "start": 82,
                    "type": "Other"
                },
                {
                    "end": 122,
                    "normalized_text": "Eleanor",
                    "probability": 0.7176,
                    "start": 116,
                    "type": "Other"
                },
                {
                    "end": 132,
                    "normalized_text": "Vicky",
                    "probability": 0.8248,
                    "start": 128,
                    "type": "Other"
                }
            ],
            "hashtags": [
                {
                    "end": 26,
                    "start": 19,
                    "tag": "Carers"
                }
            ],
            "urls": [
                {
                    "description": "Blog from Centrica about their Carers Network and the impact that they have made.",
                    "display_url": "brnw.ch/21wEdpU",
                    "end": 269,
                    "expanded_url": "https://brnw.ch/21wEdpU",
                    "start": 246,
                    "status": 200,
                    "title": "Carers Network: Taking Action, Making Impact",
                    "unwound_url": "https://www.centrica.com/stories/2023/carers-network-taking-action-making-impact/",
                    "url": "https://t.co/DRKThNwI0w"
                },
                {
                    "display_url": "pic.twitter.com/FHNVbLyf84",
                    "end": 293,
                    "expanded_url": "https://twitter.com/centricaplc/status/1721822323114758263/photo/1",
                    "media_key": "3_1721822320774316032",
                    "start": 270,
                    "url": "https://t.co/FHNVbLyf84"
                }
            ]
        },
        "id": "1721822323114758263",
        "lang": "en",
        "public_metrics": {
            "bookmark_count": 0,
            "impression_count": 299,
            "like_count": 1,
            "quote_count": 0,
            "reply_count": 0,
            "retweet_count": 0
        },
        "text": "Paving the way for #Carers across the UK...\n\nIn our latest blog, we hear from our Centrica Carers Network Co-Chairs Eleanor and Vicky as they reflect on how we\u2019re making sure our carers, and carers across the country, get the support they need \ud83d\udc49 https://t.co/DRKThNwI0w https://t.co/FHNVbLyf84"
    }
}