{
    "1658800675680051200": {
        "author_id": "5383942",
        "created_at": "2023-05-17T11:44:34.000Z",
        "edit_history_tweet_ids": [
            "1658800675680051200"
        ],
        "entities": {
            "annotations": [
                {
                    "end": 56,
                    "normalized_text": "GSKIMPACTUK Awards",
                    "probability": 0.8671,
                    "start": 39,
                    "type": "Other"
                },
                {
                    "end": 71,
                    "normalized_text": "YouTube",
                    "probability": 0.9506,
                    "start": 65,
                    "type": "Other"
                }
            ],
            "hashtags": [
                {
                    "end": 50,
                    "start": 38,
                    "tag": "GSKIMPACTUK"
                }
            ],
            "mentions": [
                {
                    "end": 13,
                    "id": "18045120",
                    "start": 0,
                    "username": "TheKingsFund"
                }
            ],
            "urls": [
                {
                    "display_url": "youtube.com/watch?v=O_L68n\u2026",
                    "end": 122,
                    "expanded_url": "https://www.youtube.com/watch?v=O_L68nKuQGs",
                    "start": 99,
                    "status": 200,
                    "unwound_url": "https://www.youtube.com/watch?v=O_L68nKuQGs",
                    "url": "https://t.co/jgnn98Iv2W"
                }
            ]
        },
        "id": "1658800675680051200",
        "lang": "en",
        "public_metrics": {
            "bookmark_count": 0,
            "impression_count": 2210,
            "like_count": 7,
            "quote_count": 0,
            "reply_count": 1,
            "retweet_count": 1
        },
        "text": "@TheKingsFund You can live stream the #GSKIMPACTUK Awards on our YouTube channel from 6:10PM BST \ud83d\udc47\nhttps://t.co/jgnn98Iv2W"
    }
}