{
    "1665715865558319106": {
        "author_id": "5383942",
        "created_at": "2023-06-05T13:43:04.000Z",
        "edit_history_tweet_ids": [
            "1665715865558319106"
        ],
        "entities": {
            "annotations": [
                {
                    "end": 45,
                    "normalized_text": "India",
                    "probability": 0.9789,
                    "start": 41,
                    "type": "Place"
                }
            ],
            "mentions": [
                {
                    "end": 12,
                    "id": "1665037531036151811",
                    "start": 0,
                    "username": "Ravi_Goyal1"
                }
            ],
            "urls": [
                {
                    "description": "How can we help you? Share your comments/ queries or feedback with us.",
                    "display_url": "india-pharma.gsk.com/en-in/contact-\u2026",
                    "end": 197,
                    "expanded_url": "https://india-pharma.gsk.com/en-in/contact-us/",
                    "images": [
                        {
                            "height": 315,
                            "url": "https://pbs.twimg.com/news_img/1721537738195845120/9QlnAUT-?format=jpg&name=orig",
                            "width": 600
                        },
                        {
                            "height": 150,
                            "url": "https://pbs.twimg.com/news_img/1721537738195845120/9QlnAUT-?format=jpg&name=150x150",
                            "width": 150
                        }
                    ],
                    "start": 174,
                    "status": 200,
                    "title": "Contact Us | GSK India",
                    "unwound_url": "https://india-pharma.gsk.com/en-in/contact-us/",
                    "url": "https://t.co/1fFJ3lDjev"
                }
            ]
        },
        "id": "1665715865558319106",
        "lang": "en",
        "public_metrics": {
            "bookmark_count": 0,
            "impression_count": 32,
            "like_count": 0,
            "quote_count": 0,
            "reply_count": 0,
            "retweet_count": 0
        },
        "text": "@Ravi_Goyal1 Hello - Our local office in India is best equipped to speak with you regarding products. You will find all the available contact information for that team here: https://t.co/1fFJ3lDjev\n\nPlease note that our offices are not open in the evenings or on weekends."
    }
}