{
    "1630272941035335680": {
        "author_id": "76117579",
        "created_at": "2023-02-27T18:25:32.000Z",
        "edit_history_tweet_ids": [
            "1630272941035335680"
        ],
        "entities": {
            "mentions": [
                {
                    "end": 10,
                    "id": "572684618",
                    "start": 0,
                    "username": "AmilcarDX"
                }
            ]
        },
        "id": "1630272941035335680",
        "lang": "pt",
        "public_metrics": {
            "bookmark_count": 0,
            "impression_count": 14,
            "like_count": 1,
            "quote_count": 0,
            "reply_count": 0,
            "retweet_count": 0
        },
        "text": "@AmilcarDX Bravo \ud83d\udc4f"
    }
}