{
    "1656017349458239488": {
        "author_id": "76117579",
        "created_at": "2023-05-09T19:24:38.000Z",
        "edit_history_tweet_ids": [
            "1656017349458239488"
        ],
        "entities": {
            "annotations": [
                {
                    "end": 62,
                    "normalized_text": "SAP TechEd",
                    "probability": 0.5025,
                    "start": 53,
                    "type": "Organization"
                },
                {
                    "end": 178,
                    "normalized_text": "US",
                    "probability": 0.9745,
                    "start": 177,
                    "type": "Place"
                },
                {
                    "end": 218,
                    "normalized_text": "Bangalore",
                    "probability": 0.95,
                    "start": 210,
                    "type": "Place"
                }
            ],
            "mentions": [
                {
                    "end": 14,
                    "id": "908762540334878720",
                    "start": 0,
                    "username": "JelenaAtLarge"
                }
            ]
        },
        "id": "1656017349458239488",
        "lang": "en",
        "public_metrics": {
            "bookmark_count": 0,
            "impression_count": 3560,
            "like_count": 2,
            "quote_count": 1,
            "reply_count": 0,
            "retweet_count": 0
        },
        "text": "@JelenaAtLarge We appreciate your strong interest in SAP TechEd. We want to make sure to reach all developers around the world. Last year, we hosted our hybrid event out of the US \u2013 this year we\u2019ll bring it to Bangalore with a great virtual experience as well!"
    }
}