{
    "1736752425782919256": {
        "author_id": "76117579",
        "created_at": "2023-12-18T14:17:00.000Z",
        "edit_history_tweet_ids": [
            "1736752425782919256"
        ],
        "entities": {
            "mentions": [
                {
                    "end": 14,
                    "id": "634338098",
                    "start": 0,
                    "username": "FrankGeisler1"
                }
            ]
        },
        "id": "1736752425782919256",
        "lang": "en",
        "public_metrics": {
            "bookmark_count": 0,
            "impression_count": 11,
            "like_count": 1,
            "quote_count": 0,
            "reply_count": 1,
            "retweet_count": 0
        },
        "text": "@FrankGeisler1 Another success! Great job \ud83d\ude0a"
    }
}