{
    "1740462840857743474": {
        "author_id": "295325513",
        "created_at": "2023-12-28T20:00:52.000Z",
        "edit_history_tweet_ids": [
            "1740462840857743474"
        ],
        "id": "1740462840857743474",
        "lang": "en",
        "public_metrics": {
            "bookmark_count": 1,
            "impression_count": 12162,
            "like_count": 270,
            "quote_count": 0,
            "reply_count": 1,
            "retweet_count": 6
        },
        "text": "A shelf"
    }
}