{
    "1686588046458724353": {
        "attachments": {
            "media_keys": [
                "13_1686587637258133504"
            ]
        },
        "author_id": "393757140",
        "created_at": "2023-08-02T04:01:40.000Z",
        "edit_history_tweet_ids": [
            "1686588046458724353"
        ],
        "entities": {
            "annotations": [
                {
                    "end": 273,
                    "normalized_text": "EarthOvershootDay",
                    "probability": 0.8598,
                    "start": 257,
                    "type": "Other"
                }
            ],
            "hashtags": [
                {
                    "end": 191,
                    "start": 179,
                    "tag": "MoveTheDate"
                },
                {
                    "end": 255,
                    "start": 241,
                    "tag": "ImpactCompany"
                },
                {
                    "end": 274,
                    "start": 256,
                    "tag": "EarthOvershootDay"
                }
            ],
            "mentions": [
                {
                    "end": 129,
                    "id": "984105765555310594",
                    "start": 115,
                    "username": "Plain_Nicolas"
                },
                {
                    "end": 149,
                    "id": "878696122344198144",
                    "start": 134,
                    "username": "Gwenaelle_huet"
                }
            ],
            "urls": [
                {
                    "display_url": "spr.ly/6011Pw6PF",
                    "end": 240,
                    "expanded_url": "http://spr.ly/6011Pw6PF",
                    "start": 217,
                    "status": 200,
                    "unwound_url": "https://perspectives.se.com/energy-efficiency/schneider-electric-let-s-movethedate-of-earth-overshoot-day?utm_source=TWITTER&utm_medium=organic_social&utm_term=SchneiderElec&utm_content=10842723266&utm_campaign=Sustainability&country=Global",
                    "url": "https://t.co/QlmfIrJDlE"
                },
                {
                    "display_url": "pic.twitter.com/nCPQlwrA8T",
                    "end": 298,
                    "expanded_url": "https://twitter.com/SchneiderElec/status/1686588046458724353/video/1",
                    "media_key": "13_1686587637258133504",
                    "start": 275,
                    "url": "https://t.co/nCPQlwrA8T"
                }
            ]
        },
        "id": "1686588046458724353",
        "lang": "en",
        "public_metrics": {
            "bookmark_count": 0,
            "impression_count": 2756,
            "like_count": 22,
            "quote_count": 2,
            "reply_count": 1,
            "retweet_count": 11
        },
        "text": "On Aug 2, we have used 70% more resources than what the \ud83c\udf0e can produce in a year, but this is reversible. Hear from @Plain_Nicolas and @Gwenaelle_huet about actions we can take to #MoveTheDate. The time to act is now: https://t.co/QlmfIrJDlE\n#ImpactCompany #EarthOvershootDay https://t.co/nCPQlwrA8T"
    }
}