{
    "1703801390361932155": {
        "author_id": "109224937",
        "created_at": "2023-09-18T16:01:21.000Z",
        "edit_history_tweet_ids": [
            "1703801390361932155"
        ],
        "entities": {
            "annotations": [
                {
                    "end": 57,
                    "normalized_text": "Agriculture",
                    "probability": 0.551,
                    "start": 47,
                    "type": "Other"
                }
            ],
            "hashtags": [
                {
                    "end": 245,
                    "start": 228,
                    "tag": "UnileverInsights"
                }
            ]
        },
        "id": "1703801390361932155",
        "lang": "en",
        "public_metrics": {
            "bookmark_count": 0,
            "impression_count": 2862,
            "like_count": 13,
            "quote_count": 2,
            "reply_count": 16,
            "retweet_count": 2
        },
        "text": "The impact results from our first Regenerative Agriculture projects are in\u2026and it\u2019s good news with our projects delivering: \n\nmore biodiversity \ud83d\udc1d \n\nimproved water efficiency \ud83d\udca7 \n\nbetter soil health. \ud83c\udf31 \n\nRead the full story here. #UnileverInsights"
    }
}