{
    "1673224620730728450": {
        "attachments": {
            "media_keys": [
                "3_1673224599725539328"
            ]
        },
        "author_id": "95291408",
        "created_at": "2023-06-26T07:00:11.000Z",
        "edit_history_tweet_ids": [
            "1673224620730728450"
        ],
        "entities": {
            "annotations": [
                {
                    "end": 233,
                    "normalized_text": "WhyEE",
                    "probability": 0.4878,
                    "start": 229,
                    "type": "Other"
                }
            ],
            "hashtags": [
                {
                    "end": 234,
                    "start": 228,
                    "tag": "WhyEE"
                },
                {
                    "end": 252,
                    "start": 235,
                    "tag": "EnergyEfficiency"
                }
            ],
            "urls": [
                {
                    "display_url": "bit.ly/3NwXKiK",
                    "end": 226,
                    "expanded_url": "https://bit.ly/3NwXKiK",
                    "start": 203,
                    "unwound_url": "https://www.whyenergyefficiency.com/solutions/allsolutions/roadmap-for-decarbonizing-cities?utm_source=social&utm_medium=twitter&utm_campaign=cf_whitepaperdecarbonizingcities&utm_content=organic_group",
                    "url": "https://t.co/du8H2042Kz"
                },
                {
                    "display_url": "pic.twitter.com/PjUMvzPftl",
                    "end": 276,
                    "expanded_url": "https://twitter.com/Danfoss/status/1673224620730728450/photo/1",
                    "media_key": "3_1673224599725539328",
                    "start": 253,
                    "url": "https://t.co/PjUMvzPftl"
                }
            ]
        },
        "id": "1673224620730728450",
        "lang": "en",
        "public_metrics": {
            "bookmark_count": 0,
            "impression_count": 726,
            "like_count": 7,
            "quote_count": 0,
            "reply_count": 0,
            "retweet_count": 3
        },
        "text": "Supermarkets, data centers, and wastewater facilities can all be turned from heavy energy consumers into crucial energy suppliers. But how? \n\nLearn more in our latest whitepaper on decarbonizing cities: https://t.co/du8H2042Kz\n\n#WhyEE #EnergyEfficiency https://t.co/PjUMvzPftl"
    }
}