{
    "1694378977643626537": {
        "attachments": {
            "media_keys": [
                "3_1694378975009689601"
            ]
        },
        "author_id": "819791",
        "created_at": "2023-08-23T16:00:02.000Z",
        "edit_history_tweet_ids": [
            "1694378977643626537"
        ],
        "entities": {
            "annotations": [
                {
                    "end": 30,
                    "normalized_text": "Future Health Index 2023",
                    "probability": 0.5637,
                    "start": 7,
                    "type": "Other"
                },
                {
                    "end": 34,
                    "normalized_text": "USA",
                    "probability": 0.9759,
                    "start": 32,
                    "type": "Place"
                }
            ],
            "hashtags": [
                {
                    "end": 128,
                    "start": 115,
                    "tag": "HealthEquity"
                }
            ],
            "urls": [
                {
                    "display_url": "to.philips/6017Po3u3",
                    "end": 257,
                    "expanded_url": "http://to.philips/6017Po3u3",
                    "start": 234,
                    "status": 200,
                    "unwound_url": "https://www.weforum.org/agenda/2023/05/how-can-the-private-sector-help-advance-health-equity/",
                    "url": "https://t.co/592zdYAWss"
                },
                {
                    "display_url": "pic.twitter.com/QcrdIK0z65",
                    "end": 281,
                    "expanded_url": "https://twitter.com/Philips/status/1694378977643626537/photo/1",
                    "media_key": "3_1694378975009689601",
                    "start": 258,
                    "url": "https://t.co/QcrdIK0z65"
                }
            ]
        },
        "id": "1694378977643626537",
        "lang": "en",
        "public_metrics": {
            "bookmark_count": 0,
            "impression_count": 1568,
            "like_count": 0,
            "quote_count": 0,
            "reply_count": 2,
            "retweet_count": 1
        },
        "text": "In our Future Health Index 2023 USA report, 82% of healthcare leaders say they are developing or intend to develop #HealthEquity initiatives. How can we work together to advance health equity? Share your thoughts and learn more here: https://t.co/592zdYAWss https://t.co/QcrdIK0z65"
    }
}