{
    "1233150062118789122": {
        "author_id": "1112667704010436609",
        "created_at": "2020-02-27T22:01:00.000Z",
        "edit_history_tweet_ids": [
            "1233150062118789122"
        ],
        "entities": {
            "annotations": [
                {
                    "end": 101,
                    "normalized_text": "Tom Cunningham",
                    "probability": 0.9784,
                    "start": 88,
                    "type": "Person"
                }
            ],
            "urls": [
                {
                    "display_url": "eu.usatoday.com/story/news/nat\u2026",
                    "end": 175,
                    "expanded_url": "https://eu.usatoday.com/story/news/nation/2020/02/16/wind-energy-can-help-american-farmers-earn-money-avoid-bankruptcy/4695670002/",
                    "start": 152,
                    "url": "https://t.co/xrmGSCSSUI"
                }
            ]
        },
        "id": "1233150062118789122",
        "lang": "en",
        "public_metrics": {
            "bookmark_count": 0,
            "impression_count": 0,
            "like_count": 1,
            "quote_count": 0,
            "reply_count": 0,
            "retweet_count": 0
        },
        "text": "\u201cI would say the absence of financial stress has been a real game-changer for me,\u201d said Tom Cunningham, who has three turbines on his land. Find more \ud83d\udc47\nhttps://t.co/xrmGSCSSUI"
    }
}