{
    "1642834304253194242": {
        "attachments": {
            "media_keys": [
                "3_1642834301606567938"
            ]
        },
        "author_id": "23045838",
        "created_at": "2023-04-03T10:19:55.000Z",
        "edit_history_tweet_ids": [
            "1642834304253194242"
        ],
        "entities": {
            "mentions": [
                {
                    "end": 155,
                    "id": "185190144",
                    "start": 141,
                    "username": "LASK_Official"
                }
            ],
            "urls": [
                {
                    "description": "Das Projekt LIFE+ Network Danube Plus verkn\u00fcpft die Lebensr\u00e4ume entlang der VERBUND-Donaukraftwerk Altenw\u00f6rth und Greifenstein.",
                    "display_url": "life-network-danube-plus.at",
                    "end": 229,
                    "expanded_url": "https://www.life-network-danube-plus.at/",
                    "start": 206,
                    "status": 200,
                    "title": "Das Projekt LIFE+ Network Danube Plus",
                    "unwound_url": "https://www.life-network-danube-plus.at/",
                    "url": "https://t.co/92f0vVvoTP"
                },
                {
                    "display_url": "pic.twitter.com/9Dywo9bRE8",
                    "end": 253,
                    "expanded_url": "https://twitter.com/verbundag/status/1642834304253194242/photo/1",
                    "media_key": "3_1642834301606567938",
                    "start": 230,
                    "url": "https://t.co/9Dywo9bRE8"
                }
            ]
        },
        "id": "1642834304253194242",
        "lang": "de",
        "public_metrics": {
            "bookmark_count": 0,
            "impression_count": 628,
            "like_count": 6,
            "quote_count": 0,
            "reply_count": 1,
            "retweet_count": 2
        },
        "text": "Unsere Fischwanderhilfe Altenw\u00f6rth ist selbst im Fr\u00fchling so sch\u00f6n, dass sie den (in solchen Dingen angeblich sehr anspruchsvollen) Fans des @LASK_Official zusagt. \nMehr zum gesamten Projekt \u00fcbrigens hier: https://t.co/92f0vVvoTP https://t.co/9Dywo9bRE8"
    }
}